PyExpUtils/FileSystemContext.py
PyExpUtils/__init__.py
PyExpUtils/collection/Collector.py
PyExpUtils/collection/Sampler.py
PyExpUtils/collection/__init__.py
PyExpUtils/collection/utils.py
PyExpUtils/models/Config.py
PyExpUtils/models/ExperimentDescription.py
PyExpUtils/models/__init__.py
PyExpUtils/parallel_runner.py
PyExpUtils/py.typed
PyExpUtils/results/Collection.py
PyExpUtils/results/LazyCollection.py
PyExpUtils/results/__init__.py
PyExpUtils/results/_utils/shared.py
PyExpUtils/results/indices.py
PyExpUtils/results/migrations.py
PyExpUtils/results/pandas.py
PyExpUtils/results/sqlite.py
PyExpUtils/results/sqlite_utils.py
PyExpUtils/results/tools.py
PyExpUtils/results/voting.py
PyExpUtils/runner/Slurm.py
PyExpUtils/runner/__init__.py
PyExpUtils/runner/parallel.py
PyExpUtils/runner/parallel_exec.py
PyExpUtils/runner/utils.py
PyExpUtils/utils/NestedDict.py
PyExpUtils/utils/__init__.py
PyExpUtils/utils/arrays.py
PyExpUtils/utils/asyncio.py
PyExpUtils/utils/cache.py
PyExpUtils/utils/cmdline.py
PyExpUtils/utils/csv.py
PyExpUtils/utils/dict.py
PyExpUtils/utils/fp.py
PyExpUtils/utils/generator.py
PyExpUtils/utils/iterable.py
PyExpUtils/utils/jit.py
PyExpUtils/utils/pandas.py
PyExpUtils/utils/path.py
PyExpUtils/utils/permute.py
PyExpUtils/utils/random.py
PyExpUtils/utils/str.py
PyExpUtils/utils/types.py
PyExpUtils_andnp-8.1.2.dist-info/entry_points.txt
PyExpUtils_andnp-8.1.2.dist-info/WHEEL
PyExpUtils_andnp-8.1.2.dist-info/METADATA
PyExpUtils_andnp-8.1.2.dist-info/RECORD
