Metadata-Version: 2.1
Name: PyExpUtils-andnp
Version: 8.1.2
Summary: A small set of utilities for RL and ML experiments
License: MIT
Author-email: Andy Patterson <andnpatterson@gmail.com>
Requires-Python: >=3.10
Requires-Dist: connectorx
Requires-Dist: filelock>=3.0.0
Requires-Dist: numba>=0.57.0
Requires-Dist: numpy>=1.21.5
Requires-Dist: pandas
Provides-Extra: dev
Requires-Dist: ruff; extra == "dev"
Requires-Dist: commitizen; extra == "dev"
Requires-Dist: pre-commit; extra == "dev"
Requires-Dist: types-filelock; extra == "dev"
Requires-Dist: build; extra == "dev"
Requires-Dist: twine; extra == "dev"
Requires-Dist: pyright>=1.1.324; extra == "dev"
